README.md
setup.py
PythonForTheLab/__init__.py
PythonForTheLab/__main__.py
PythonForTheLab/start.py
PythonForTheLab/Controller/__init__.py
PythonForTheLab/Controller/lantz_daq.py
PythonForTheLab/Controller/simple_daq.py
PythonForTheLab/Controller/visa_daq.py
PythonForTheLab/Model/__init__.py
PythonForTheLab/Model/daq/__init__.py
PythonForTheLab/Model/daq/analog_daq.py
PythonForTheLab/Model/daq/base.py
PythonForTheLab/Model/daq/dummy_daq.py
PythonForTheLab/Model/daq/lantz_daq.py
PythonForTheLab/Model/daq/visa_daq.py
PythonForTheLab/Model/experiment/IV_measurement.py
PythonForTheLab/Model/experiment/__init__.py
PythonForTheLab/View/__init__.py
PythonForTheLab/View/config_window.py
PythonForTheLab/View/general_worker.py
PythonForTheLab/View/monitor_window.py
PythonForTheLab/View/scan_window.py
PythonForTheLab/View/start.py
py4lab.egg-info/PKG-INFO
py4lab.egg-info/SOURCES.txt
py4lab.egg-info/dependency_links.txt
py4lab.egg-info/entry_points.txt
py4lab.egg-info/requires.txt
py4lab.egg-info/top_level.txt
testsuite/__init__.py
testsuite/test_dummy_daq.py