Metadata-Version: 2.1
Name: py4lab
Version: 0.1.2
Summary: Code for Python for the Lab Workshop
Home-page: https://github.com/PFTL/SimpleDaq
Author: Aquiles Carattino
Author-email: aquiles@uetke.com
License: GPLv3
Platform: UNKNOWN
Classifier: Programming Language :: Python :: 3
Classifier: Programming Language :: Python :: 3.6
Classifier: Programming Language :: Python :: 3.7
